Metadata-Version: 2.1
Name: dbgz
Version: 0.5.4
Summary: Python library to load DBGZ files
Home-page: https://github.com/filipinascimento/dbgz
Author: Filipi N. Silva
Author-email: filipi@iu.edu
Classifier: Programming Language :: Python :: 3
Classifier: License :: OSI Approved :: MIT License
Classifier: Operating System :: OS Independent
Requires-Python: >=3.5
License-File: LICENSE
